pybcoin/__init__.py
pybcoin/home.py
pybcoin/starter.py
pybcoin/DataCollector/__init__.py
pybcoin/DataCollector/btc_data_collector.py
pybcoin/DataCollector/controller_collector.py
pybcoin/DataCollector/google_trends_collector.py
pybcoin/DataCollector/market_data_collector.py
pybcoin/DataCollector/reddit_comment_collector.py
pybcoin/DataCollector/tweets_collector.py
pybcoin/ModelForecast/__init__.py
pybcoin/ModelForecast/btc_model.py
pybcoin/SentimentAnalyzer/__init__.py
pybcoin/SentimentAnalyzer/sentiment_scorer.py
pybcoin/utils/__init__.py
pybcoin/utils/pre_processing.py
pybcoin-0.15.dist-info/METADATA
pybcoin-0.15.dist-info/RECORD
pybcoin-0.15.dist-info/WHEEL
pybcoin-0.15.dist-info/top_level.txt
