Metadata-Version: 2.1
Name: pybcoin
Version: 0.15
Summary: Bitcoin Trend Forecast
Home-page: https://github.com/rguptauw/pybcoin
Author: Pushottam Shivraj
Author-email: pshivraj@uw.edu
License: UNKNOWN
Keywords: testing,Forecasting,Timeseries
Platform: UNKNOWN
Classifier: Programming Language :: Python :: 3
